README.rst
magiclog.py
setup.cfg
setup.py
magiclog.egg-info/PKG-INFO
magiclog.egg-info/SOURCES.txt
magiclog.egg-info/dependency_links.txt
magiclog.egg-info/requires.txt
magiclog.egg-info/top_level.txt